bottr/__init__.py
bottr/bot.py
bottr/util.py
bottr-0.1.4.dist-info/DESCRIPTION.rst
bottr-0.1.4.dist-info/METADATA
bottr-0.1.4.dist-info/RECORD
bottr-0.1.4.dist-info/WHEEL
bottr-0.1.4.dist-info/metadata.json
bottr-0.1.4.dist-info/top_level.txt
