Metadata-Version: 2.0
Name: bottr
Version: 0.1.4
Summary: Simple Reddit Bot Library
Home-page: http://github.com/slang03/bottr
Author: Steven Lang
Author-email: steven.lang.mz@gmail.com
License: MIT
Keywords: reddit bot praw
Platform: UNKNOWN
Classifier: Development Status :: 3 - Alpha
Classifier: License :: OSI Approved :: MIT License
Classifier: Framework :: Robot Framework :: Library
Classifier: Programming Language :: Python :: 3
Classifier: Programming Language :: Python :: 3.2
Classifier: Programming Language :: Python :: 3.3
Classifier: Programming Language :: Python :: 3.4
Classifier: Programming Language :: Python :: 3.5
Classifier: Programming Language :: Python :: 3.6
Classifier: Topic :: Internet
Requires-Dist: praw (==5.3.0)
